mpu6050/MPU6050.py
mpu6050/MPUConstants.py
mpu6050/__init__.py
mpu6050-0.0.3.dist-info/LICENSE.txt
mpu6050-0.0.3.dist-info/METADATA
mpu6050-0.0.3.dist-info/WHEEL
mpu6050-0.0.3.dist-info/top_level.txt
mpu6050-0.0.3.dist-info/RECORD
