Metadata-Version: 2.1
Name: mpu6050
Version: 0.0.3
Summary: A Python Library for Efficient MPU6050 DMP Access.
Home-page: https://github.com/OmidAlek/mpu6050
Author: Majid Alekasir
Author-email: <majid.alekasir@gmail.com>
Keywords: python,quaternion,vector,XYZVector,IMU,DMP,INS,Accelometer,Gyrometer,MPU6050,Fusion,EKF,Kalman Filter
Classifier: Development Status :: 5 - Production/Stable
Classifier: Intended Audience :: Developers
Classifier: Programming Language :: Python :: 3.10
Classifier: Operating System :: Unix
Classifier: Operating System :: MacOS :: MacOS X
License-File: LICENSE.txt
Requires-Dist: quat
Requires-Dist: smbus
